ew_crypto_lib/__init__.py
ew_crypto_lib/crypto.py
ew_crypto_lib/entities/__init__.py
ew_crypto_lib/entities/jwt_header_entity.py
ew_crypto_lib/entities/wallet_type.py
ew_crypto_lib/wallets/__init__.py
ew_crypto_lib/wallets/ew_wallet.py
ew_crypto_lib/wallets/atecc_wallet/__init__.py
ew_crypto_lib/wallets/atecc_wallet/atecc608a_wallet.py
ew_crypto_lib/wallets/file_wallet/__init__.py
ew_crypto_lib/wallets/file_wallet/file_wallet.py
ew_crypto_lib/wallets/infineon_wallet/__init__.py
ew_crypto_lib/wallets/infineon_wallet/cmd_lib_wrapper.py
ew_crypto_lib/wallets/infineon_wallet/infineon_wallet.py
ew_crypto_lib/wallets/infineon_wallet/libse_interface.so
ew_crypto_lib/wallets/iotsafe_wallet/__init__.py
ew_crypto_lib/wallets/iotsafe_wallet/iotsafe_wallet.py
tests/__init__.py
ew_crypto_lib-0.1.1a0.dist-info/LICENSE
ew_crypto_lib-0.1.1a0.dist-info/METADATA
ew_crypto_lib-0.1.1a0.dist-info/WHEEL
ew_crypto_lib-0.1.1a0.dist-info/top_level.txt
ew_crypto_lib-0.1.1a0.dist-info/RECORD
